BiliStalkerMCP/__main__.py
bilistalkermcp-1.0.0.dist-info/METADATA
bilistalkermcp-1.0.0.dist-info/WHEEL
bilistalkermcp-1.0.0.dist-info/entry_points.txt
bilistalkermcp-1.0.0.dist-info/top_level.txt
bilistalkermcp-1.0.0.dist-info/RECORD
