Metadata-Version: 2.4
Name: BiliStalkerMCP
Version: 1.0.0
Summary: MCP Server for getting Bilibili user video updates
Requires-Python: >=3.10
Requires-Dist: bilibili-api-python
Requires-Dist: fastmcp
Requires-Dist: pyyaml>=6.0
